ipylabel/__init__.py
ipylabel/_frontend.py
ipylabel/_version.py
ipylabel/example.py
ipylabel/text.py
ipylabel/types.py
ipylabel/utils.py
ipylabel/labextension/build_log.json
ipylabel/labextension/package.json
ipylabel/labextension/static/lib_index_js.7d32c3bc4b33de7feb96.js
ipylabel/labextension/static/lib_index_js.7d32c3bc4b33de7feb96.js.map
ipylabel/labextension/static/lib_plugin_js.0d7f60484b5bf35839e8.js
ipylabel/labextension/static/lib_plugin_js.0d7f60484b5bf35839e8.js.map
ipylabel/labextension/static/lib_widgets_js.22f25673ffddb7ba45d5.js
ipylabel/labextension/static/lib_widgets_js.22f25673ffddb7ba45d5.js.map
ipylabel/labextension/static/remoteEntry.e762e3b55f0d7d0a382b.js
ipylabel/labextension/static/remoteEntry.e762e3b55f0d7d0a382b.js.map
ipylabel/labextension/static/style.js
ipylabel/nbextension/extension.js
ipylabel/nbextension/index.js
ipylabel/nbextension/index.js.LICENSE.txt
ipylabel/nbextension/index.js.map
ipylabel/tests/__init__.py
ipylabel/tests/conftest.py
ipylabel/tests/test_example.py
ipylabel/tests/test_nbextension_path.py
ipylabel-0.1.7.data/data/etc/jupyter/nbconfig/notebook.d/ipylabel.json
ipylabel-0.1.7.data/data/share/jupyter/labextensions/ipylabel/build_log.json
ipylabel-0.1.7.data/data/share/jupyter/labextensions/ipylabel/install.json
ipylabel-0.1.7.data/data/share/jupyter/labextensions/ipylabel/package.json
ipylabel-0.1.7.data/data/share/jupyter/labextensions/ipylabel/static/lib_index_js.7d32c3bc4b33de7feb96.js
ipylabel-0.1.7.data/data/share/jupyter/labextensions/ipylabel/static/lib_index_js.7d32c3bc4b33de7feb96.js.map
ipylabel-0.1.7.data/data/share/jupyter/labextensions/ipylabel/static/lib_plugin_js.0d7f60484b5bf35839e8.js
ipylabel-0.1.7.data/data/share/jupyter/labextensions/ipylabel/static/lib_plugin_js.0d7f60484b5bf35839e8.js.map
ipylabel-0.1.7.data/data/share/jupyter/labextensions/ipylabel/static/lib_widgets_js.22f25673ffddb7ba45d5.js
ipylabel-0.1.7.dist-info/LICENSE.txt
ipylabel-0.1.7.dist-info/METADATA
ipylabel-0.1.7.dist-info/WHEEL
ipylabel-0.1.7.dist-info/top_level.txt
ipylabel-0.1.7.dist-info/RECORD
